envdataclass/__init__.py
envdataclass-0.4.dist-info/METADATA
envdataclass-0.4.dist-info/WHEEL
envdataclass-0.4.dist-info/top_level.txt
envdataclass-0.4.dist-info/RECORD
