Metadata-Version: 2.1
Name: envdataclass
Version: 0.4
Summary: Parses .env files against dataclass based schema validation
Home-page: UNKNOWN
Author: briccardo
Author-email: rbiagini02@gmail.com
License: MIT
Platform: UNKNOWN
Classifier: License :: OSI Approved :: MIT License
Classifier: Programming Language :: Python :: 3.8
Requires-Dist: python-dotenv
